tart2ms/__init__.py
tart2ms/casa_read_ms.py
tart2ms/fixvis.py
tart2ms/ms_helper.py
tart2ms/named_phasings.json
tart2ms/read_ms.py
tart2ms/tart2ms.py
tart2ms/util.py
tart2ms/catalogs/3CRR
tart2ms/catalogs/MeerKAT_gaincal_list
tart2ms/catalogs/SUMMS
tart2ms/catalogs/__init__.py
tart2ms/catalogs/catalog_reader.py
tart2ms/scripts/tart2ms.py
tart2ms/tests/data_test.json
tart2ms/tests/test_catalogs.py
tart2ms/tests/test_read_ms.py
tart2ms/tests/test_tart2ms.py
tart2ms-0.7.4.dist-info/METADATA
tart2ms-0.7.4.dist-info/WHEEL
tart2ms-0.7.4.dist-info/entry_points.txt
tart2ms-0.7.4.dist-info/licenses/LICENSE.txt
tart2ms-0.7.4.dist-info/RECORD
