Metadata-Version: 2.4
Name: tart2ms
Version: 0.7.4
Summary: Convert TART observation data to Measurement Sets
Project-URL: Homepage, http://github.com/tart-telescope/tart2ms
Author-email: Tim Molteno <tim@elec.ac.nz>
License-Expression: GPL-3.0-or-later
License-File: LICENSE.txt
Classifier: Development Status :: 4 - Beta
Classifier: Intended Audience :: Science/Research
Classifier: License :: OSI Approved :: GNU General Public License v3 (GPLv3)
Classifier: Operating System :: OS Independent
Classifier: Programming Language :: Python :: 3.8
Classifier: Programming Language :: Python :: 3.9
Classifier: Programming Language :: Python :: 3.10
Classifier: Programming Language :: Python :: 3.11
Classifier: Topic :: Communications :: Ham Radio
Classifier: Topic :: Scientific/Engineering
Requires-Python: <3.14,>=3.11
Requires-Dist: astropy<8.0.0,>=7.1.0
Requires-Dist: codex-africanus<0.5,>=0.4.2
Requires-Dist: dask-ms<0.3.0,>=0.2.0
Requires-Dist: h5py<4.0.0,>=3.1.0
Requires-Dist: numpy<3.0.0,>=1.6.0
Requires-Dist: pandas<3.0.0,>=2.0.0
Requires-Dist: progress<2.0.0,>=1.6.1
Requires-Dist: python-casacore<4.0.0,>=3.7.1
Requires-Dist: requests<3.0.0,>=2.32.4
Requires-Dist: scipy<2.0.0,>=1.16.1
Requires-Dist: tart-tools>=1.4.0
Requires-Dist: tart>=1.4.0
